<?xml version="1.0" encoding="UTF-8"?><record_update table="ais_dictionary">
    <ais_dictionary action="INSERT_OR_UPDATE">
        <active>true</active>
        <auto_refresh>24</auto_refresh>
        <blocked_field/>
        <case_sensitive>false</case_sensitive>
        <data_source>x_1319361_fluency_incident</data_source>
        <derived>true</derived>
        <field/>
        <label>fluency2 Search Profile Default Spell Check Dictionary</label>
        <last_derived/>
        <locale>en</locale>
        <name>x_1319361_fluency_fluency2_search_profile_default_spell_check_dictionary</name>
        <publish_id/>
        <punctuation_sensitive>false</punctuation_sensitive>
        <state>NEW</state>
        <sys_class_name>ais_dictionary</sys_class_name>
        <sys_created_by>admin</sys_created_by>
        <sys_created_on>2024-02-16 17:55:18</sys_created_on>
        <sys_id>fcdb841b97144210caadba6de053afa5</sys_id>
        <sys_mod_count>0</sys_mod_count>
        <sys_name>x_1319361_fluency_fluency2_search_profile_default_spell_check_dictionary</sys_name>
        <sys_package display_value="fluency" source="x_1319361_fluency">8ac9780397948210caadba6de053af86</sys_package>
        <sys_policy/>
        <sys_scope display_value="fluency">8ac9780397948210caadba6de053af86</sys_scope>
        <sys_update_name>ais_dictionary_fcdb841b97144210caadba6de053afa5</sys_update_name>
        <sys_updated_by>admin</sys_updated_by>
        <sys_updated_on>2024-02-16 17:55:18</sys_updated_on>
        <type>SPELLCHECK</type>
    </ais_dictionary>
</record_update>
